odoo8_addon_l10n_br_stock_account_report-8.0.1.0.0.99.dev4-py2.7-nspkg.pth
odoo8_addon_l10n_br_stock_account_report-8.0.1.0.0.99.dev4.dist-info/METADATA
odoo8_addon_l10n_br_stock_account_report-8.0.1.0.0.99.dev4.dist-info/RECORD
odoo8_addon_l10n_br_stock_account_report-8.0.1.0.0.99.dev4.dist-info/WHEEL
odoo8_addon_l10n_br_stock_account_report-8.0.1.0.0.99.dev4.dist-info/namespace_packages.txt
odoo8_addon_l10n_br_stock_account_report-8.0.1.0.0.99.dev4.dist-info/top_level.txt
odoo_addons/l10n_br_stock_account_report/README.rst
odoo_addons/l10n_br_stock_account_report/__init__.py
odoo_addons/l10n_br_stock_account_report/__openerp__.py
odoo_addons/l10n_br_stock_account_report/report/__init__.py
odoo_addons/l10n_br_stock_account_report/report/stock_valuation_history_xls.py
odoo_addons/l10n_br_stock_account_report/static/description/icon.png
odoo_addons/l10n_br_stock_account_report/wizard/__init__.py
odoo_addons/l10n_br_stock_account_report/wizard/stock_valuation_history.py
odoo_addons/l10n_br_stock_account_report/wizard/stock_valuation_history_view.xml
